{
 "document": {
  "width": 16,
  "height": 16,
  "grid": {
   "x": 1,
   "y": 1
  }
 },
 "palette": [
  "#000000",
  "#0000ff",
  "#00ff00",
  "#00ffff",
  "#ff0000",
  "#ff00ff",
  "#ffff00",
  "#ffffff",
  "#808080",
  "#000080",
  "#008000",
  "#008080",
  "#800000",
  "#800080",
  "#808000",
  "#c0c0c0",
  "#000000",
  "#202020",
  "#404040",
  "#606060",
  "#808080",
  "#a0a0a0",
  "#c0c0c0",
  "#e0e0e0",
  "#adff2f",
  "#afeeee",
  "#b0c4de",
  "#b0e0e6",
  "#b22222",
  "#b8860b",
  "#ba55d3",
  "#bc8f8f",
  "#bdb76b",
  "#c0c0c0",
  "#c71585",
  "#cd5c5c",
  "#cd853f",
  "#d2691e",
  "#d2b48c",
  "#d3d3d3"
 ],
 "root": {
  "type": "Group",
  "name": null,
  "id": "a74f4ab3-65a1-453c-abf3-a4aa1604fc78",
  "list": [
   {
    "type": "Shape",
    "name": "lineT",
    "id": "4de27664-5567-4ec5-a87e-362df95a41f2",
    "list": [],
    "visible": true,
    "lock": false,
    "img": null,
    "x": 7,
    "y": 0,
    "w": 9,
    "h": 16,
    "rotate": 0,
    "rxSep": false,
    "rx1": 0,
    "rx2": 0,
    "rx3": 0,
    "rx4": 0,
    "shape": [
     {
      "x": 7,
      "y": 16
     },
     {
      "x": 7,
      "y": 16
     },
     {
      "x": 7,
      "y": 16
     },
     {
      "x": 7,
      "y": 0
     },
     {
      "x": 7,
      "y": 0
     },
     {
      "x": 7,
      "y": 0
     },
     {
      "x": 9,
      "y": 0
     },
     {
      "x": 9,
      "y": 0
     },
     {
      "x": 9,
      "y": 0
     },
     {
      "x": 9,
      "y": 10
     },
     {
      "x": 9,
      "y": 10
     },
     {
      "x": 9,
      "y": 10
     },
     {
      "x": 16,
      "y": 10
     },
     {
      "x": 16,
      "y": 10
     },
     {
      "x": 16,
      "y": 10
     },
     {
      "x": 16,
      "y": 12
     },
     {
      "x": 16,
      "y": 12
     },
     {
      "x": 16,
      "y": 12
     },
     {
      "x": 9,
      "y": 12
     },
     {
      "x": 9,
      "y": 12
     },
     {
      "x": 9,
      "y": 12
     },
     {
      "x": 9,
      "y": 16
     },
     {
      "x": 9,
      "y": 16
     },
     {
      "x": 9,
      "y": 16
     }
    ],
    "shapeOrgX": 7,
    "shapeOrgY": 0,
    "shapeOrgW": 9,
    "shapeOrgH": 16,
    "shapeClose": true,
    "imageFrames": 1,
    "polyVertex": 5,
    "polyDepth": 100,
    "polyTopWidth": 0,
    "polyBottomWidth": 0,
    "text": "Text",
    "font": "sans-serif",
    "textBold": false,
    "textItalic": false,
    "textAlign": "left",
    "textFit": true,
    "colFill1": "#c0c0c0",
    "colFill1Alpha": 100,
    "colFill2": "#202020",
    "colFill2Alpha": 100,
    "colStroke": "#000000",
    "colStrokeAlpha": 100,
    "colShadow": "#000000",
    "colGradation": "none",
    "colGradX1": 0.1,
    "colGradY1": 0.1,
    "colGradX2": 0.9,
    "colGradY2": 0.9,
    "fill": true,
    "stroke": false,
    "lineWidth": 1,
    "lineJoin": "round",
    "lineCap": "round",
    "blur": 0,
    "embossWidth": 4,
    "embossDepth": 0,
    "embossBlur": 50,
    "textureType": "None",
    "textureDepth": 0,
    "textureZoom": 100,
    "shadowOffX": 8,
    "shadowOffY": 8,
    "shadowDepth": 0,
    "shadowBlur": 8
   },
   {
    "type": "Shape",
    "name": "lineL",
    "id": "aca0ff75-35b1-44f2-b0f7-7a4531ed9c81",
    "list": [],
    "visible": false,
    "lock": false,
    "img": null,
    "x": 7,
    "y": 0,
    "w": 9,
    "h": 12,
    "rotate": 0,
    "rxSep": false,
    "rx1": 0,
    "rx2": 0,
    "rx3": 0,
    "rx4": 0,
    "shape": [
     {
      "x": 7,
      "y": 0
     },
     {
      "x": 7,
      "y": 0
     },
     {
      "x": 7,
      "y": 0
     },
     {
      "x": 9,
      "y": 0
     },
     {
      "x": 9,
      "y": 0
     },
     {
      "x": 9,
      "y": 0
     },
     {
      "x": 9,
      "y": 10
     },
     {
      "x": 9,
      "y": 10
     },
     {
      "x": 9,
      "y": 10
     },
     {
      "x": 16,
      "y": 10
     },
     {
      "x": 16,
      "y": 10
     },
     {
      "x": 16,
      "y": 10
     },
     {
      "x": 16,
      "y": 12
     },
     {
      "x": 16,
      "y": 12
     },
     {
      "x": 16,
      "y": 12
     },
     {
      "x": 7,
      "y": 12
     },
     {
      "x": 7,
      "y": 12
     },
     {
      "x": 7,
      "y": 12
     }
    ],
    "shapeOrgX": 7,
    "shapeOrgY": 0,
    "shapeOrgW": 9,
    "shapeOrgH": 12,
    "shapeClose": true,
    "imageFrames": 1,
    "polyVertex": 5,
    "polyDepth": 100,
    "polyTopWidth": 0,
    "polyBottomWidth": 0,
    "text": "Text",
    "font": "sans-serif",
    "textBold": false,
    "textItalic": false,
    "textAlign": "left",
    "textFit": true,
    "colFill1": "#c0c0c0",
    "colFill1Alpha": 100,
    "colFill2": "#202020",
    "colFill2Alpha": 100,
    "colStroke": "#000000",
    "colStrokeAlpha": 100,
    "colShadow": "#000000",
    "colGradation": "none",
    "colGradX1": 0.1,
    "colGradY1": 0.1,
    "colGradX2": 0.9,
    "colGradY2": 0.9,
    "fill": true,
    "stroke": false,
    "lineWidth": 1,
    "lineJoin": "round",
    "lineCap": "round",
    "blur": 0,
    "embossWidth": 4,
    "embossDepth": 0,
    "embossBlur": 50,
    "textureType": "None",
    "textureDepth": 0,
    "textureZoom": 100,
    "shadowOffX": 8,
    "shadowOffY": 8,
    "shadowDepth": 0,
    "shadowBlur": 8
   },
   {
    "type": "Rect",
    "name": "lineI",
    "id": "e4683461-2070-427e-a6f0-c8dbe966fd69",
    "list": [],
    "visible": false,
    "lock": false,
    "img": null,
    "x": 7,
    "y": 0,
    "w": 2,
    "h": 16,
    "rotate": 0,
    "rxSep": false,
    "rx1": 0,
    "rx2": 0,
    "rx3": 0,
    "rx4": 0,
    "shape": [],
    "shapeOrgX": 0,
    "shapeOrgY": 0,
    "shapeOrgW": 0,
    "shapeOrgH": 0,
    "shapeClose": true,
    "imageFrames": 1,
    "polyVertex": 5,
    "polyDepth": 100,
    "polyTopWidth": 0,
    "polyBottomWidth": 0,
    "text": "Text",
    "font": "sans-serif",
    "textBold": false,
    "textItalic": false,
    "textAlign": "left",
    "textFit": true,
    "colFill1": "#c0c0c0",
    "colFill1Alpha": 100,
    "colFill2": "#202020",
    "colFill2Alpha": 100,
    "colStroke": "#000000",
    "colStrokeAlpha": 100,
    "colShadow": "#000000",
    "colGradation": "none",
    "colGradX1": 0.1,
    "colGradY1": 0.1,
    "colGradX2": 0.9,
    "colGradY2": 0.9,
    "fill": true,
    "stroke": false,
    "lineWidth": 1,
    "lineJoin": "round",
    "lineCap": "round",
    "blur": 0,
    "embossWidth": 4,
    "embossDepth": 0,
    "embossBlur": 50,
    "textureType": "None",
    "textureDepth": 0,
    "textureZoom": 100,
    "shadowOffX": 8,
    "shadowOffY": 8,
    "shadowDepth": 0,
    "shadowBlur": 8
   },
   {
    "type": "Rect",
    "name": null,
    "id": "bb318b15-a8f1-4c85-9326-d660ccf1a1da",
    "list": [],
    "visible": false,
    "lock": false,
    "img": null,
    "x": 0,
    "y": 0,
    "w": 16,
    "h": 16,
    "rotate": 0,
    "rxSep": false,
    "rx1": 0,
    "rx2": 0,
    "rx3": 0,
    "rx4": 0,
    "shape": [],
    "shapeOrgX": 0,
    "shapeOrgY": 0,
    "shapeOrgW": 0,
    "shapeOrgH": 0,
    "shapeClose": true,
    "imageFrames": 1,
    "polyVertex": 5,
    "polyDepth": 100,
    "polyTopWidth": 0,
    "polyBottomWidth": 0,
    "text": "Text",
    "font": "sans-serif",
    "textBold": false,
    "textItalic": false,
    "textAlign": "left",
    "textFit": true,
    "colFill1": "#000000",
    "colFill1Alpha": 100,
    "colFill2": "#202020",
    "colFill2Alpha": 100,
    "colStroke": "#000000",
    "colStrokeAlpha": 100,
    "colShadow": "#000000",
    "colGradation": "none",
    "colGradX1": 0.1,
    "colGradY1": 0.1,
    "colGradX2": 0.9,
    "colGradY2": 0.9,
    "fill": true,
    "stroke": true,
    "lineWidth": 1,
    "lineJoin": "round",
    "lineCap": "round",
    "blur": 0,
    "embossWidth": 4,
    "embossDepth": 0,
    "embossBlur": 50,
    "textureType": "None",
    "textureDepth": 0,
    "textureZoom": 100,
    "shadowOffX": 8,
    "shadowOffY": 8,
    "shadowDepth": 0,
    "shadowBlur": 8
   }
  ],
  "visible": true,
  "lock": false,
  "img": null,
  "x": 0,
  "y": 0,
  "w": 1024,
  "h": 768,
  "rotate": 0,
  "rxSep": false,
  "rx1": 0,
  "rx2": 0,
  "rx3": 0,
  "rx4": 0,
  "shape": [],
  "shapeOrgX": 0,
  "shapeOrgY": 0,
  "shapeOrgW": 0,
  "shapeOrgH": 0,
  "shapeClose": true,
  "imageFrames": 1,
  "polyVertex": 5,
  "polyDepth": 100,
  "polyTopWidth": 0,
  "polyBottomWidth": 0,
  "text": "Text",
  "font": "sans-serif",
  "textBold": false,
  "textItalic": false,
  "textAlign": "left",
  "textFit": true,
  "colFill1": "#8090a0",
  "colFill1Alpha": 100,
  "colFill2": "#202020",
  "colFill2Alpha": 100,
  "colStroke": "#000000",
  "colStrokeAlpha": 100,
  "colShadow": "#000000",
  "colGradation": "none",
  "colGradX1": 0.1,
  "colGradY1": 0.1,
  "colGradX2": 0.9,
  "colGradY2": 0.9,
  "fill": true,
  "stroke": true,
  "lineWidth": 1,
  "lineJoin": "round",
  "lineCap": "round",
  "blur": 0,
  "embossWidth": 4,
  "embossDepth": 0,
  "embossBlur": 50,
  "textureType": "None",
  "textureDepth": 0,
  "textureZoom": 100,
  "shadowOffX": 8,
  "shadowOffY": 8,
  "shadowDepth": 0,
  "shadowBlur": 8
 }
}